genanki/__init__.py
genanki/apkg_col.py
genanki/apkg_schema.py
genanki/builtin_models.py
genanki/card.py
genanki/deck.py
genanki/model.py
genanki/note.py
genanki/package.py
genanki/util.py
genanki/version.py
genanki-0.13.0.dist-info/LICENSE.txt
genanki-0.13.0.dist-info/METADATA
genanki-0.13.0.dist-info/WHEEL
genanki-0.13.0.dist-info/top_level.txt
genanki-0.13.0.dist-info/RECORD
