Metadata-Version: 2.1
Name: genanki
Version: 0.13.0
Summary: Generate Anki decks programmatically
Home-page: http://github.com/kerrickstaley/genanki
Author: Kerrick Staley
Author-email: k@kerrickstaley.com
License: MIT
Keywords: anki,flashcards,memorization
Platform: UNKNOWN
Requires-Python: >=3.6
License-File: LICENSE.txt
